odoo/addons/account_partner_company_group/README.rst
odoo/addons/account_partner_company_group/__init__.py
odoo/addons/account_partner_company_group/__manifest__.py
odoo/addons/account_partner_company_group/hooks.py
odoo/addons/account_partner_company_group/i18n/account_partner_company_group.pot
odoo/addons/account_partner_company_group/i18n/es.po
odoo/addons/account_partner_company_group/i18n/it.po
odoo/addons/account_partner_company_group/i18n/partner_company_group.pot
odoo/addons/account_partner_company_group/i18n/pt_BR.po
odoo/addons/account_partner_company_group/i18n/zh_CN.po
odoo/addons/account_partner_company_group/models/__init__.py
odoo/addons/account_partner_company_group/models/account_move.py
odoo/addons/account_partner_company_group/readme/CONTRIBUTORS.md
odoo/addons/account_partner_company_group/readme/CREDITS.md
odoo/addons/account_partner_company_group/readme/DESCRIPTION.md
odoo/addons/account_partner_company_group/static/description/icon.png
odoo/addons/account_partner_company_group/static/description/index.html
odoo/addons/account_partner_company_group/views/account_move_views.xml
odoo_addon_account_partner_company_group-18.0.1.0.0.3.dist-info/METADATA
odoo_addon_account_partner_company_group-18.0.1.0.0.3.dist-info/WHEEL
odoo_addon_account_partner_company_group-18.0.1.0.0.3.dist-info/top_level.txt
odoo_addon_account_partner_company_group-18.0.1.0.0.3.dist-info/RECORD
